epik/__init__.py
epik/kernel.py
epik/model.py
epik/settings.py
epik/utils.py
epik-0.1.0.dist-info/LICENSE
epik-0.1.0.dist-info/METADATA
epik-0.1.0.dist-info/WHEEL
epik-0.1.0.dist-info/entry_points.txt
epik-0.1.0.dist-info/top_level.txt
epik-0.1.0.dist-info/RECORD
