Metadata-Version: 2.1
Name: epik
Version: 0.1.0
Summary: Epistatic Kernels for GPU-accelerated Gaussian process regression
Author-email: Carlos Martí-Gómez <martigo@cshl.edu>
License: MIT
Project-URL: Documentation, https://epik.readthedocs.io
Project-URL: Repository, https://github.com/cmarti/epik.git
Keywords: genotype-phenotype maps,fitness landscape,gaussian process
Classifier: Programming Language :: Python :: 3
Classifier: Intended Audience :: Science/Research
Classifier: License :: OSI Approved :: MIT License
Classifier: Operating System :: OS Independent
Requires-Python: >=3.8
License-File: LICENSE
Requires-Dist: tqdm
Requires-Dist: numpy
Requires-Dist: pandas
Requires-Dist: torch
Requires-Dist: gpytorch >=1.11
Requires-Dist: pykeops
